[
  {
    "timestamp": "2026-01-31T17:09:23.320Z",
    "data": {
      "code": 200,
      "data": {
        "fallbackFlag": false,
        "info": {
          "has_audio_list": [
            true
          ],
          "media_ids": [
            "CAUSJGJkNjg0Yzk5LTg1NDktNGJjYi05N2I0LTI0OTY2ZmQ4NjNjMRokM2QyMmIwNWItMzQ4Ni00MTJkLTgyYTktYmQ3NGQyZDAxNTUxIgNDQUUqJDdkN2ExMDZkLTFhMGEtNGY1ZC1hOGM1LTk2MDI5NTQ4NGVkOQ"
          ],
          "resolution": "720p",
          "resultUrls": [
            "https://tempfile.aiquickdraw.com/v/2b99cb6a3648f7b6eba3f74ad4314e8a_1769879360.mp4"
          ],
          "result_urls": [
            "https://tempfile.aiquickdraw.com/v/2b99cb6a3648f7b6eba3f74ad4314e8a_1769879360.mp4"
          ],
          "seeds": [
            65581
          ]
        },
        "promptJson": "{\"aspectRatio\":\"9:16\",\"callBackUrl\":\"https://clawdbot.clawdbotsina.cloud/api/video-callback\",\"enableFallback\":false,\"enableTranslation\":true,\"generationType\":\"FIRST_AND_LAST_FRAMES_2_VIDEO\",\"imageUrls\":[\"https://tmpfiles.org/dl/22000950/da2d0aa2-da5d-4a61-992a-4eeda0554678.jpg\"],\"model\":\"veo3_fast\",\"prompt\":\"The woman transforms into a cute fluffy kiwi bird. Her body shrinks, her floral blouse becomes soft brown kiwi feathers. She wobbles around on tiny bird legs making adorable kiwi sounds. The coffee cup looks giant now. Very funny comedy transformation, bewildered bird expression.\"}",
        "taskId": "2b99cb6a3648f7b6eba3f74ad4314e8a"
      },
      "msg": "Video generated successfully."
    }
  },
  {
    "timestamp": "2026-01-31T17:32:09.856Z",
    "data": {
      "code": 200,
      "data": {
        "fallbackFlag": false,
        "info": {
          "has_audio_list": [
            true
          ],
          "media_ids": [
            "CAUSJGNiNjNiNjFlLTA3MDEtNDM5ZS05NTM0LTVmNTFkN2JkOWU0MRokZjM5NGI5NjctN2NjNy00Nzk3LWJlNWYtZTVlYTVhNmFhYjg1IgNDQUUqJGY0ZTg5MzE5LWQ0OTgtNGRiMC1iYmVlLTIzZDk0N2U1YTA2Nw"
          ],
          "resolution": "720p",
          "resultUrls": [
            "https://tempfile.aiquickdraw.com/v/91a30717d5dc08d1a5a5a4ecab8d03d8_1769880727.mp4"
          ],
          "result_urls": [
            "https://tempfile.aiquickdraw.com/v/91a30717d5dc08d1a5a5a4ecab8d03d8_1769880727.mp4"
          ],
          "seeds": [
            52817
          ]
        },
        "promptJson": "{\"aspectRatio\":\"9:16\",\"callBackUrl\":\"https://clawdbot.clawdbotsina.cloud/api/video-callback\",\"enableFallback\":false,\"enableTranslation\":true,\"generationType\":\"FIRST_AND_LAST_FRAMES_2_VIDEO\",\"imageUrls\":[\"http://tmpfiles.org/dl/22003582/45fe8c57-4d4d-46cf-8eb9-9458074edc5a.jpg\"],\"model\":\"veo3_fast\",\"prompt\":\"The man transforms into a terrifying dark superhero. His eyes glow red with intense power. A black armored suit materializes around him with sharp edges and glowing red veins of energy. Dark smoke and lightning crackle around him. His cape billows dramatically in supernatural wind. He clenches his fist and energy explodes outward. Menacing, powerful, like a villain-hero hybrid. Epic cinematic transformation, dark and scary atmosphere.\"}",
        "taskId": "91a30717d5dc08d1a5a5a4ecab8d03d8"
      },
      "msg": "Video generated successfully."
    }
  },
  {
    "timestamp": "2026-02-01T14:23:48.667Z",
    "data": {
      "code": 200,
      "data": {
        "fallbackFlag": false,
        "info": {
          "has_audio_list": [
            true
          ],
          "media_ids": [
            "CAUSJGZiYTM1YTJlLTQxY2EtNDkzOS1hY2FhLTU4ZDRiOTk5MTIzOBokYTM3ZmY3OWUtZDVkYS00ZmJmLTk3MWUtZWY5ODFiYzJmNjgxIgNDQUUqJDNhMTZmNzQzLTQ3OTQtNGUyNi1iYjBjLWJkMGU1ZTc0NDE3YQ"
          ],
          "resolution": "720p",
          "resultUrls": [
            "https://tempfile.aiquickdraw.com/v/da8023dac2a8866990d7b2ad290fe00b_1769955826.mp4"
          ],
          "result_urls": [
            "https://tempfile.aiquickdraw.com/v/da8023dac2a8866990d7b2ad290fe00b_1769955826.mp4"
          ],
          "seeds": [
            30120
          ]
        },
        "promptJson": "{\"aspectRatio\":\"9:16\",\"callBackUrl\":\"https://clawdbot.clawdbotsina.cloud/api/video-callback\",\"enableFallback\":false,\"enableTranslation\":true,\"generationType\":\"FIRST_AND_LAST_FRAMES_2_VIDEO\",\"imageUrls\":[\"http://tmpfiles.org/dl/22116979/4705a0a2-9be4-481e-9576-a8de3691a896.jpg\"],\"model\":\"veo3_fast\",\"prompt\":\"The person slowly transforms into a glamorous anthropomorphic pickle wearing sunglasses and a tiny crown. The pickle version strikes confident poses, winks at the camera, and does a little dance. Dramatic lighting, sparkle effects, smooth morphing transition. Funny and stylish vibe.\"}",
        "taskId": "da8023dac2a8866990d7b2ad290fe00b"
      },
      "msg": "Video generated successfully."
    }
  }
]